indented_logs/__init__.py
indented_logs/decorators.py
indented_logs-1.0.4.dist-info/LICENSE
indented_logs-1.0.4.dist-info/METADATA
indented_logs-1.0.4.dist-info/WHEEL
indented_logs-1.0.4.dist-info/top_level.txt
indented_logs-1.0.4.dist-info/RECORD
