Metadata-Version: 2.1
Name: indented-logs
Version: 1.0.4
Summary: Decorators to indent-log function calls with parameter and timing
Home-page: https://github.com/cuongbm/indented_logs
Author: Cuong Bui
Author-email: buiminhcuong@hotmail.com
License: UNKNOWN
Project-URL: Bug Tracker, https://github.com/cuongbm/indented_logs/issues
Platform: UNKNOWN
Classifier: Programming Language :: Python :: 3
Classifier: License :: OSI Approved :: MIT License
Classifier: Operating System :: OS Independent
Requires-Python: >=3.6
License-File: LICENSE
